{"RPT":{"ScanTime":"0.37 sec.","ScanFile":"20150823_luxblox_55d9306c22add7159150823023108_scan.json","Warnings":null},"SRV":{"WEB":{"ALL":"Good","model":true},"PHP":{"ALL":"Good","openbase":true,"maxtime":true,"mysqli":true},"WP":{"ALL":"Good","version":true,"core":true,"cache":true}},"ARC":{"Size":"0B","DirCount":"0","FileCount":"0","FullCount":"0","FilterInfo":{"Dirs":{"Warning":[],"Unreadable":[],"Core":["\/Users\/cklegan\/Developer\/apache\/htdocs\/luxblox\/wp\/wp-snapshots"],"Instance":["\/Users\/cklegan\/Developer\/apache\/htdocs\/luxblox"]},"Files":{"Size":[],"Warning":[],"Unreadable":[],"Core":[],"Instance":[]},"Exts":{"Core":[],"Instance":[]}},"Status":{"Size":"Good","Names":"Good","Big":"Good"},"Dirs":[],"Files":[]},"DB":{"Status":{"Success":true,"Size":"Good","Rows":"Good"},"Size":"9.08MB","Rows":"13,229","TableCount":114,"TableList":{"wp_lux_2_commentmeta":{"Rows":"0","Size":"48KB"},"wp_lux_2_comments":{"Rows":"1","Size":"96KB"},"wp_lux_2_duplicator_packages":{"Rows":"0","Size":"32KB"},"wp_lux_2_links":{"Rows":"0","Size":"32KB"},"wp_lux_2_options":{"Rows":"212","Size":"1.2MB"},"wp_lux_2_pmxi_files":{"Rows":"0","Size":"16KB"},"wp_lux_2_pmxi_history":{"Rows":"0","Size":"16KB"},"wp_lux_2_pmxi_imports":{"Rows":"0","Size":"16KB"},"wp_lux_2_pmxi_posts":{"Rows":"0","Size":"16KB"},"wp_lux_2_pmxi_templates":{"Rows":"0","Size":"16KB"},"wp_lux_2_postmeta":{"Rows":"364","Size":"304KB"},"wp_lux_2_postmeta_bak":{"Rows":"1","Size":"48KB"},"wp_lux_2_posts":{"Rows":"101","Size":"336KB"},"wp_lux_2_revslider_css":{"Rows":"47","Size":"16KB"},"wp_lux_2_revslider_layer_animations":{"Rows":"0","Size":"16KB"},"wp_lux_2_revslider_settings":{"Rows":"0","Size":"16KB"},"wp_lux_2_revslider_sliders":{"Rows":"0","Size":"16KB"},"wp_lux_2_revslider_slides":{"Rows":"0","Size":"16KB"},"wp_lux_2_revslider_static_slides":{"Rows":"0","Size":"16KB"},"wp_lux_2_term_relationships":{"Rows":"1","Size":"32KB"},"wp_lux_2_term_taxonomy":{"Rows":"5","Size":"48KB"},"wp_lux_2_terms":{"Rows":"5","Size":"48KB"},"wp_lux_2_woocommerce_api_keys":{"Rows":"0","Size":"48KB"},"wp_lux_2_woocommerce_attribute_taxonomies":{"Rows":"0","Size":"32KB"},"wp_lux_2_woocommerce_downloadable_product_permissions":{"Rows":"0","Size":"48KB"},"wp_lux_2_woocommerce_order_itemmeta":{"Rows":"0","Size":"48KB"},"wp_lux_2_woocommerce_order_items":{"Rows":"0","Size":"32KB"},"wp_lux_2_woocommerce_tax_rate_locations":{"Rows":"0","Size":"64KB"},"wp_lux_2_woocommerce_tax_rates":{"Rows":"0","Size":"80KB"},"wp_lux_2_woocommerce_termmeta":{"Rows":"0","Size":"48KB"},"wp_lux_3_city_log":{"Rows":"0","Size":"16KB"},"wp_lux_3_commentmeta":{"Rows":"0","Size":"48KB"},"wp_lux_3_comments":{"Rows":"0","Size":"96KB"},"wp_lux_3_countries":{"Rows":"239","Size":"80KB"},"wp_lux_3_duplicator_packages":{"Rows":"0","Size":"32KB"},"wp_lux_3_links":{"Rows":"0","Size":"32KB"},"wp_lux_3_multicity":{"Rows":"3","Size":"16KB"},"wp_lux_3_options":{"Rows":"174","Size":"1.14MB"},"wp_lux_3_pmxi_files":{"Rows":"0","Size":"16KB"},"wp_lux_3_pmxi_history":{"Rows":"0","Size":"16KB"},"wp_lux_3_pmxi_imports":{"Rows":"0","Size":"16KB"},"wp_lux_3_pmxi_posts":{"Rows":"0","Size":"16KB"},"wp_lux_3_pmxi_templates":{"Rows":"0","Size":"16KB"},"wp_lux_3_post_expire_session":{"Rows":"0","Size":"16KB"},"wp_lux_3_postcodes":{"Rows":"0","Size":"16KB"},"wp_lux_3_postmeta":{"Rows":"1,035","Size":"208KB"},"wp_lux_3_posts":{"Rows":"63","Size":"80KB"},"wp_lux_3_ratings":{"Rows":"0","Size":"16KB"},"wp_lux_3_revslider_css":{"Rows":"47","Size":"16KB"},"wp_lux_3_revslider_layer_animations":{"Rows":"0","Size":"16KB"},"wp_lux_3_revslider_settings":{"Rows":"0","Size":"16KB"},"wp_lux_3_revslider_sliders":{"Rows":"0","Size":"16KB"},"wp_lux_3_revslider_slides":{"Rows":"0","Size":"16KB"},"wp_lux_3_revslider_static_slides":{"Rows":"0","Size":"16KB"},"wp_lux_3_term_relationships":{"Rows":"24","Size":"32KB"},"wp_lux_3_term_taxonomy":{"Rows":"5","Size":"48KB"},"wp_lux_3_terms":{"Rows":"5","Size":"48KB"},"wp_lux_3_transactions":{"Rows":"0","Size":"16KB"},"wp_lux_3_users_packageperlist":{"Rows":"0","Size":"16KB"},"wp_lux_3_woocommerce_api_keys":{"Rows":"0","Size":"48KB"},"wp_lux_3_woocommerce_attribute_taxonomies":{"Rows":"0","Size":"32KB"},"wp_lux_3_woocommerce_downloadable_product_permissions":{"Rows":"0","Size":"48KB"},"wp_lux_3_woocommerce_order_itemmeta":{"Rows":"0","Size":"48KB"},"wp_lux_3_woocommerce_order_items":{"Rows":"0","Size":"32KB"},"wp_lux_3_woocommerce_tax_rate_locations":{"Rows":"0","Size":"64KB"},"wp_lux_3_woocommerce_tax_rates":{"Rows":"0","Size":"80KB"},"wp_lux_3_woocommerce_termmeta":{"Rows":"0","Size":"48KB"},"wp_lux_3_zones":{"Rows":"3,917","Size":"192KB"},"wp_lux_blog_versions":{"Rows":"0","Size":"32KB"},"wp_lux_blogs":{"Rows":"3","Size":"48KB"},"wp_lux_city_log":{"Rows":"0","Size":"16KB"},"wp_lux_commentmeta":{"Rows":"2","Size":"48KB"},"wp_lux_comments":{"Rows":"1","Size":"96KB"},"wp_lux_countries":{"Rows":"271","Size":"64KB"},"wp_lux_duplicator_packages":{"Rows":"3","Size":"32KB"},"wp_lux_links":{"Rows":"0","Size":"32KB"},"wp_lux_multicity":{"Rows":"3","Size":"16KB"},"wp_lux_options":{"Rows":"967","Size":"1.36MB"},"wp_lux_pmxi_files":{"Rows":"0","Size":"16KB"},"wp_lux_pmxi_history":{"Rows":"0","Size":"16KB"},"wp_lux_pmxi_imports":{"Rows":"0","Size":"16KB"},"wp_lux_pmxi_posts":{"Rows":"0","Size":"16KB"},"wp_lux_pmxi_templates":{"Rows":"0","Size":"16KB"},"wp_lux_post_expire_session":{"Rows":"4","Size":"16KB"},"wp_lux_postcodes":{"Rows":"1","Size":"16KB"},"wp_lux_postmeta":{"Rows":"1,058","Size":"304KB"},"wp_lux_posts":{"Rows":"114","Size":"336KB"},"wp_lux_ratings":{"Rows":"0","Size":"16KB"},"wp_lux_registration_log":{"Rows":"2","Size":"32KB"},"wp_lux_revslider_css":{"Rows":"47","Size":"16KB"},"wp_lux_revslider_layer_animations":{"Rows":"0","Size":"16KB"},"wp_lux_revslider_settings":{"Rows":"1","Size":"16KB"},"wp_lux_revslider_sliders":{"Rows":"0","Size":"16KB"},"wp_lux_revslider_slides":{"Rows":"0","Size":"16KB"},"wp_lux_revslider_static_slides":{"Rows":"0","Size":"16KB"},"wp_lux_signups":{"Rows":"0","Size":"80KB"},"wp_lux_site":{"Rows":"1","Size":"32KB"},"wp_lux_sitemeta":{"Rows":"33","Size":"80KB"},"wp_lux_term_relationships":{"Rows":"108","Size":"32KB"},"wp_lux_term_taxonomy":{"Rows":"39","Size":"48KB"},"wp_lux_terms":{"Rows":"39","Size":"48KB"},"wp_lux_transactions":{"Rows":"1","Size":"16KB"},"wp_lux_usermeta":{"Rows":"137","Size":"48KB"},"wp_lux_users":{"Rows":"5","Size":"48KB"},"wp_lux_users_packageperlist":{"Rows":"0","Size":"16KB"},"wp_lux_woocommerce_api_keys":{"Rows":"0","Size":"48KB"},"wp_lux_woocommerce_attribute_taxonomies":{"Rows":"0","Size":"32KB"},"wp_lux_woocommerce_downloadable_product_permissions":{"Rows":"0","Size":"48KB"},"wp_lux_woocommerce_order_itemmeta":{"Rows":"0","Size":"48KB"},"wp_lux_woocommerce_order_items":{"Rows":"0","Size":"32KB"},"wp_lux_woocommerce_tax_rate_locations":{"Rows":"0","Size":"64KB"},"wp_lux_woocommerce_tax_rates":{"Rows":"1","Size":"80KB"},"wp_lux_woocommerce_termmeta":{"Rows":"2","Size":"48KB"},"wp_lux_zones":{"Rows":"4,137","Size":"192KB"}}}}